honeybee_vtk/__init__.py
honeybee_vtk/_geometry.py
honeybee_vtk/_helper.py
honeybee_vtk/actor.py
honeybee_vtk/assistant.py
honeybee_vtk/camera.py
honeybee_vtk/config.py
honeybee_vtk/filter.py
honeybee_vtk/headless.py
honeybee_vtk/image_processing.py
honeybee_vtk/legend_parameter.py
honeybee_vtk/model.py
honeybee_vtk/scene.py
honeybee_vtk/text_actor.py
honeybee_vtk/time_step_images.py
honeybee_vtk/to_vtk.py
honeybee_vtk/types.py
honeybee_vtk/assets/PollinationViewer.html
honeybee_vtk/cli/__init__.py
honeybee_vtk/cli/config.py
honeybee_vtk/cli/export.py
honeybee_vtk/cli/post_process.py
honeybee_vtk/cli/translate.py
honeybee_vtk/vtkjs/__init__.py
honeybee_vtk/vtkjs/helper.py
honeybee_vtk/vtkjs/schema.py
honeybee_vtk-0.39.1.dist-info/LICENSE
honeybee_vtk-0.39.1.dist-info/METADATA
honeybee_vtk-0.39.1.dist-info/WHEEL
honeybee_vtk-0.39.1.dist-info/entry_points.txt
honeybee_vtk-0.39.1.dist-info/top_level.txt
honeybee_vtk-0.39.1.dist-info/RECORD
